logwatcher/__init__.py
logwatcher/log_file_watcher.py
py_logwatcher-0.0.0.dist-info/DESCRIPTION.rst
py_logwatcher-0.0.0.dist-info/METADATA
py_logwatcher-0.0.0.dist-info/RECORD
py_logwatcher-0.0.0.dist-info/WHEEL
py_logwatcher-0.0.0.dist-info/metadata.json
py_logwatcher-0.0.0.dist-info/top_level.txt
tests/__init__.py
