Metadata-Version: 2.0
Name: py-logwatcher
Version: 0.0.0
Summary: Python implementation of tail -- A log file watcher
Home-page: https://github.com/tonytan4ever/py-logwatcher
Author: Tony Tan
Author-email: tonytan198211@gmail.com
License: MIT
Download-URL: https://github.com/tonytan4ever/py-logwatcher/archive/0.0.tar.gz
Platform: any
Classifier: Development Status :: 4 - Beta
Classifier: Intended Audience :: Developers
Classifier: Intended Audience :: System Administrators
Classifier: License :: OSI Approved :: MIT License
Classifier: Operating System :: OS Independent
Classifier: Environment :: Console
Classifier: Programming Language :: Python :: 2
Classifier: Programming Language :: Python :: 3
Classifier: Topic :: System :: Shells
Classifier: Topic :: System :: Systems Administration
Classifier: Topic :: Software Development :: Libraries :: Python Modules
